{
  "source_file": "data/input/20240419_Inhumations silos (1).xlsx",
  "reference_sites_csv": "data/output/sites.csv",
  "aggregated_site_keys": [
    "bergheim|saulager|1024900|6797050",
    "berstett|langenberg|1044400|6851000",
    "bischoffsheim|bischenberg|1032000|6829850",
    "blaesheim|lotissement entree est|1040550|6832950",
    "breuschwickersheim|vogelsgesang|1038300|6841500",
    "colmar|les aubepines|1023850|6782500",
    "dachstein|geist|1033700|6838650",
    "didenheim|kahlberg|1022200|6744700",
    "dingsheim|haspelacker cos 4 1|1041950|6846400",
    "duntzenheim|rainwasen lgv 8 4|1035050|6855750",
    "eguisheim|rte d herrlisheim|1021100|6779900",
    "entzheim|aeroparc lidl|1043700|6837100",
    "erstein|grassweg|1042900|6824850",
    "ettendorf|gaentzbruch|1036050|6867100",
    "geispolsheim|schwobenfeld|1043700|6836650",
    "gougenheim|gingsheimer feld|1037850|6855300",
    "gougenheim|steinbrunnen|1037050|6855300",
    "goxwiller valff|zac paei|1032450|6823750",
    "griesheim sur souffel|flaschen|1023900|6782500",
    "schiltigheim|37 rue d adelshoffen|1050150|6844800",
    "hochfelden|rd421|1034900|6860200",
    "ittenheim|achenheimer berg cos 2 11|1039600|6842400",
    "kolbsheim|herenweg cos 2 6|1037550|6840050",
    "marlenheim|rue du general de gaulle|1030750|6845050",
    "meistratzheim|foegel|1036300|6826550",
    "meistratzheim|pfett station d epuration|1023900|6782500",
    "mittelhausen|langmatt lgv 9 3|1040150|6854600",
    "mittelhausen|liesbuehl gimbretter weg lgv 10 1|1039850|6854750",
    "mittelhausen|vorderen berg|1039250|6854950",
    "morschwiller le bas|rocade ouest|1021000|6745200",
    "obernai|schulbach|1031750|6826650",
    "rosheim|leimen|1029550|6831250",
    "rosheim|rosenmeer|1031850|6831950",
    "souffelweyersheim|les sept arpents|1048850|6847250",
    "strasbourg|rue des comtes|1047450|6842100",
    "ensisheim|reguisheimer feld zaid tranche 3|1026150|6761950",
    "wettolsheim|ricoh|1021950|6781000",
    "wolfisheim|westermatt|noc|noc",
    "colmar|route de rouffach|noc|noc",
    "didenheim|kahlberg diag|noc|noc",
    "gundolsheim|muhlmatt a remplir|noc|noc",
    "marckolsheim|schlettstadterfeld|noc|noc",
    "duntzenheim|lgv inrap|noc|noc",
    "duntzenheim|ebenheit lgv stock nord 2 1|noc|noc",
    "schnersheim|za behlenheimerweg|noc|noc"
  ],
  "matches": [
    {
      "agg_key": "bergheim|saulager|1024900|6797050",
      "match_existing_site_id": null,
      "is_new": true,
      "merge_candidate": false,
      "x_l93": 1024887.0,
      "y_l93": 6797044.0,
      "has_coords": true,
      "nom_site": "Bergheim - Saulager",
      "commune": "Bergheim",
      "pays": "FR"
    },
    {
      "agg_key": "berstett|langenberg|1044400|6851000",
      "match_existing_site_id": null,
      "is_new": true,
      "merge_candidate": false,
      "x_l93": 1044392.0,
      "y_l93": 6850994.0,
      "has_coords": true,
      "nom_site": "Berstett - Langenberg",
      "commune": "Berstett",
      "pays": "FR"
    },
    {
      "agg_key": "bischoffsheim|bischenberg|1032000|6829850",
      "match_existing_site_id": null,
      "is_new": true,
      "merge_candidate": false,
      "x_l93": 1032025.0,
      "y_l93": 6829834.0,
      "has_coords": true,
      "nom_site": "Bischoffsheim - Bischenberg",
      "commune": "Bischoffsheim",
      "pays": "FR"
    },
    {
      "agg_key": "blaesheim|lotissement entree est|1040550|6832950",
      "match_existing_site_id": "SITE-355f46c130ae782a",
      "is_new": false,
      "merge_candidate": false,
      "x_l93": 1040545.0,
      "y_l93": 6832941.0,
      "has_coords": true,
      "nom_site": "Blaesheim - Lotissement Entrée Est",
      "commune": "Blaesheim",
      "pays": "FR"
    },
    {
      "agg_key": "breuschwickersheim|vogelsgesang|1038300|6841500",
      "match_existing_site_id": null,
      "is_new": true,
      "merge_candidate": false,
      "x_l93": 1038289.0,
      "y_l93": 6841523.0,
      "has_coords": true,
      "nom_site": "Breuschwickersheim - Vogelsgesang",
      "commune": "Breuschwickersheim",
      "pays": "FR"
    },
    {
      "agg_key": "colmar|les aubepines|1023850|6782500",
      "match_existing_site_id": null,
      "is_new": true,
      "merge_candidate": false,
      "x_l93": 1023863.0,
      "y_l93": 6782512.0,
      "has_coords": true,
      "nom_site": "Colmar - Les Aubépines",
      "commune": "Colmar",
      "pays": "FR"
    },
    {
      "agg_key": "dachstein|geist|1033700|6838650",
      "match_existing_site_id": null,
      "is_new": true,
      "merge_candidate": false,
      "x_l93": 1033692.0,
      "y_l93": 6838638.0,
      "has_coords": true,
      "nom_site": "Dachstein - Geist",
      "commune": "Dachstein",
      "pays": "FR"
    },
    {
      "agg_key": "didenheim|kahlberg|1022200|6744700",
      "match_existing_site_id": "SITE-633f31d70e73e834",
      "is_new": false,
      "merge_candidate": false,
      "x_l93": 1022216.0,
      "y_l93": 6744716.0,
      "has_coords": true,
      "nom_site": "Didenheim - Kahlberg",
      "commune": "Didenheim",
      "pays": "FR"
    },
    {
      "agg_key": "dingsheim|haspelacker cos 4 1|1041950|6846400",
      "match_existing_site_id": null,
      "is_new": true,
      "merge_candidate": false,
      "x_l93": 1041952.0,
      "y_l93": 6846403.0,
      "has_coords": true,
      "nom_site": "Dingsheim - Haspelacker - COS 4.1",
      "commune": "Dingsheim",
      "pays": "FR"
    },
    {
      "agg_key": "duntzenheim|rainwasen lgv 8 4|1035050|6855750",
      "match_existing_site_id": null,
      "is_new": true,
      "merge_candidate": false,
      "x_l93": 1035064.0,
      "y_l93": 6855731.0,
      "has_coords": true,
      "nom_site": "Duntzenheim - Rainwasen, LGV 8-4",
      "commune": "Duntzenheim",
      "pays": "FR"
    },
    {
      "agg_key": "eguisheim|rte d herrlisheim|1021100|6779900",
      "match_existing_site_id": null,
      "is_new": true,
      "merge_candidate": false,
      "x_l93": 1021102.0,
      "y_l93": 6779910.0,
      "has_coords": true,
      "nom_site": "Eguisheim - Rte d'Herrlisheim",
      "commune": "Eguisheim",
      "pays": "FR"
    },
    {
      "agg_key": "entzheim|aeroparc lidl|1043700|6837100",
      "match_existing_site_id": "SITE-199c449d850d698e",
      "is_new": false,
      "merge_candidate": false,
      "x_l93": 1043713.0,
      "y_l93": 6837098.0,
      "has_coords": true,
      "nom_site": "Entzheim - Aéroparc-Lidl",
      "commune": "Entzheim",
      "pays": "FR"
    },
    {
      "agg_key": "erstein|grassweg|1042900|6824850",
      "match_existing_site_id": null,
      "is_new": true,
      "merge_candidate": false,
      "x_l93": 1042915.0,
      "y_l93": 6824866.0,
      "has_coords": true,
      "nom_site": "Erstein - Grassweg",
      "commune": "Erstein",
      "pays": "FR"
    },
    {
      "agg_key": "ettendorf|gaentzbruch|1036050|6867100",
      "match_existing_site_id": "SITE-c7bb40201db1d25b",
      "is_new": false,
      "merge_candidate": false,
      "x_l93": 1036049.0,
      "y_l93": 6867096.0,
      "has_coords": true,
      "nom_site": "Ettendorf - Gaentzbruch",
      "commune": "Ettendorf",
      "pays": "FR"
    },
    {
      "agg_key": "geispolsheim|schwobenfeld|1043700|6836650",
      "match_existing_site_id": null,
      "is_new": true,
      "merge_candidate": false,
      "x_l93": 1043723.0,
      "y_l93": 6836657.0,
      "has_coords": true,
      "nom_site": "Geispolsheim - Schwobenfeld",
      "commune": "Geispolsheim",
      "pays": "FR"
    },
    {
      "agg_key": "gougenheim|gingsheimer feld|1037850|6855300",
      "match_existing_site_id": "SITE-8d3922c765a66589",
      "is_new": false,
      "merge_candidate": false,
      "x_l93": 1037853.0,
      "y_l93": 6855275.0,
      "has_coords": true,
      "nom_site": "Gougenheim - Gingsheimer Feld",
      "commune": "Gougenheim",
      "pays": "FR"
    },
    {
      "agg_key": "gougenheim|steinbrunnen|1037050|6855300",
      "match_existing_site_id": null,
      "is_new": true,
      "merge_candidate": false,
      "x_l93": 1037050.0,
      "y_l93": 6855282.0,
      "has_coords": true,
      "nom_site": "Gougenheim - Steinbrunnen",
      "commune": "Gougenheim",
      "pays": "FR"
    },
    {
      "agg_key": "goxwiller valff|zac paei|1032450|6823750",
      "match_existing_site_id": "SITE-3596060c1b055d82",
      "is_new": false,
      "merge_candidate": false,
      "x_l93": 1032466.0,
      "y_l93": 6823746.0,
      "has_coords": true,
      "nom_site": "Goxwiller-Valff - ZAC PAEI",
      "commune": "Goxwiller-Valff",
      "pays": "FR"
    },
    {
      "agg_key": "griesheim sur souffel|flaschen|1023900|6782500",
      "match_existing_site_id": "SITE-e5218169732dafab",
      "is_new": false,
      "merge_candidate": false,
      "x_l93": 1023878.0,
      "y_l93": 6782508.0,
      "has_coords": true,
      "nom_site": "Griesheim sur Souffel - Flaschen",
      "commune": "Griesheim sur Souffel",
      "pays": "FR"
    },
    {
      "agg_key": "schiltigheim|37 rue d adelshoffen|1050150|6844800",
      "match_existing_site_id": null,
      "is_new": true,
      "merge_candidate": false,
      "x_l93": 1050157.0,
      "y_l93": 6844789.0,
      "has_coords": true,
      "nom_site": "Schiltigheim - 37 rue d'Adelshoffen",
      "commune": "Schiltigheim",
      "pays": "FR"
    },
    {
      "agg_key": "hochfelden|rd421|1034900|6860200",
      "match_existing_site_id": null,
      "is_new": true,
      "merge_candidate": false,
      "x_l93": 1034925.0,
      "y_l93": 6860177.0,
      "has_coords": true,
      "nom_site": "Hochfelden - RD421",
      "commune": "Hochfelden",
      "pays": "FR"
    },
    {
      "agg_key": "ittenheim|achenheimer berg cos 2 11|1039600|6842400",
      "match_existing_site_id": null,
      "is_new": true,
      "merge_candidate": false,
      "x_l93": 1039598.0,
      "y_l93": 6842391.0,
      "has_coords": true,
      "nom_site": "Ittenheim - Achenheimer Berg (COS 2-11)",
      "commune": "Ittenheim",
      "pays": "FR"
    },
    {
      "agg_key": "kolbsheim|herenweg cos 2 6|1037550|6840050",
      "match_existing_site_id": "SITE-13c8cbd1e41ba716",
      "is_new": false,
      "merge_candidate": false,
      "x_l93": 1037553.0,
      "y_l93": 6840045.0,
      "has_coords": true,
      "nom_site": "Kolbsheim - Herenweg - COS 2,6",
      "commune": "Kolbsheim",
      "pays": "FR"
    },
    {
      "agg_key": "marlenheim|rue du general de gaulle|1030750|6845050",
      "match_existing_site_id": null,
      "is_new": true,
      "merge_candidate": false,
      "x_l93": 1030749.0,
      "y_l93": 6845060.0,
      "has_coords": true,
      "nom_site": "Marlenheim - Rue du Général De Gaulle",
      "commune": "Marlenheim",
      "pays": "FR"
    },
    {
      "agg_key": "meistratzheim|foegel|1036300|6826550",
      "match_existing_site_id": null,
      "is_new": true,
      "merge_candidate": false,
      "x_l93": 1036321.0,
      "y_l93": 6826558.0,
      "has_coords": true,
      "nom_site": "Meistratzheim - Foegel",
      "commune": "Meistratzheim",
      "pays": "FR"
    },
    {
      "agg_key": "meistratzheim|pfett station d epuration|1023900|6782500",
      "match_existing_site_id": null,
      "is_new": true,
      "merge_candidate": false,
      "x_l93": 1023878.0,
      "y_l93": 6782508.0,
      "has_coords": true,
      "nom_site": "Meistratzheim - Pfett (station d'épuration)",
      "commune": "Meistratzheim",
      "pays": "FR"
    },
    {
      "agg_key": "mittelhausen|langmatt lgv 9 3|1040150|6854600",
      "match_existing_site_id": null,
      "is_new": true,
      "merge_candidate": false,
      "x_l93": 1040154.0,
      "y_l93": 6854624.0,
      "has_coords": true,
      "nom_site": "Mittelhausen - Langmatt, LGV 9-3",
      "commune": "Mittelhausen",
      "pays": "FR"
    },
    {
      "agg_key": "mittelhausen|liesbuehl gimbretter weg lgv 10 1|1039850|6854750",
      "match_existing_site_id": null,
      "is_new": true,
      "merge_candidate": false,
      "x_l93": 1039860.0,
      "y_l93": 6854762.0,
      "has_coords": true,
      "nom_site": "Mittelhausen - Liesbuehl Gimbretter Weg (LGV 10-1)",
      "commune": "Mittelhausen",
      "pays": "FR"
    },
    {
      "agg_key": "mittelhausen|vorderen berg|1039250|6854950",
      "match_existing_site_id": null,
      "is_new": true,
      "merge_candidate": false,
      "x_l93": 1039270.0,
      "y_l93": 6854967.0,
      "has_coords": true,
      "nom_site": "Mittelhausen - Vorderen Berg",
      "commune": "Mittelhausen",
      "pays": "FR"
    },
    {
      "agg_key": "morschwiller le bas|rocade ouest|1021000|6745200",
      "match_existing_site_id": "SITE-35019783110e3b5a",
      "is_new": false,
      "merge_candidate": false,
      "x_l93": 1021019.0,
      "y_l93": 6745177.0,
      "has_coords": true,
      "nom_site": "Morschwiller-le-Bas - Rocade Ouest",
      "commune": "Morschwiller-le-Bas",
      "pays": "FR"
    },
    {
      "agg_key": "obernai|schulbach|1031750|6826650",
      "match_existing_site_id": null,
      "is_new": true,
      "merge_candidate": false,
      "x_l93": 1031733.0,
      "y_l93": 6826673.0,
      "has_coords": true,
      "nom_site": "Obernai - Schulbach",
      "commune": "Obernai",
      "pays": "FR"
    },
    {
      "agg_key": "rosheim|leimen|1029550|6831250",
      "match_existing_site_id": null,
      "is_new": true,
      "merge_candidate": false,
      "x_l93": 1029548.0,
      "y_l93": 6831251.0,
      "has_coords": true,
      "nom_site": "Rosheim - Leimen",
      "commune": "Rosheim",
      "pays": "FR"
    },
    {
      "agg_key": "rosheim|rosenmeer|1031850|6831950",
      "match_existing_site_id": null,
      "is_new": true,
      "merge_candidate": false,
      "x_l93": 1031826.0,
      "y_l93": 6831961.0,
      "has_coords": true,
      "nom_site": "Rosheim - Rosenmeer",
      "commune": "Rosheim",
      "pays": "FR"
    },
    {
      "agg_key": "souffelweyersheim|les sept arpents|1048850|6847250",
      "match_existing_site_id": null,
      "is_new": true,
      "merge_candidate": false,
      "x_l93": 1048849.0,
      "y_l93": 6847232.0,
      "has_coords": true,
      "nom_site": "Souffelweyersheim - Les Sept Arpents",
      "commune": "Souffelweyersheim",
      "pays": "FR"
    },
    {
      "agg_key": "strasbourg|rue des comtes|1047450|6842100",
      "match_existing_site_id": null,
      "is_new": true,
      "merge_candidate": false,
      "x_l93": 1047430.0,
      "y_l93": 6842081.0,
      "has_coords": true,
      "nom_site": "Strasbourg - Rue des Comtes",
      "commune": "Strasbourg",
      "pays": "FR"
    },
    {
      "agg_key": "ensisheim|reguisheimer feld zaid tranche 3|1026150|6761950",
      "match_existing_site_id": null,
      "is_new": true,
      "merge_candidate": false,
      "x_l93": 1026143.0,
      "y_l93": 6761946.0,
      "has_coords": true,
      "nom_site": "Ensisheim - Reguisheimer Feld, ZAID, Tranche 3",
      "commune": "Ensisheim",
      "pays": "FR"
    },
    {
      "agg_key": "wettolsheim|ricoh|1021950|6781000",
      "match_existing_site_id": null,
      "is_new": true,
      "merge_candidate": false,
      "x_l93": 1021938.0,
      "y_l93": 6781004.0,
      "has_coords": true,
      "nom_site": "Wettolsheim - Ricoh",
      "commune": "Wettolsheim",
      "pays": "FR"
    },
    {
      "agg_key": "wolfisheim|westermatt|noc|noc",
      "match_existing_site_id": null,
      "is_new": true,
      "merge_candidate": false,
      "x_l93": null,
      "y_l93": null,
      "has_coords": false,
      "nom_site": "Wolfisheim - Westermatt",
      "commune": "Wolfisheim",
      "pays": "FR"
    },
    {
      "agg_key": "colmar|route de rouffach|noc|noc",
      "match_existing_site_id": null,
      "is_new": true,
      "merge_candidate": false,
      "x_l93": null,
      "y_l93": null,
      "has_coords": false,
      "nom_site": "Colmar - Route de Rouffach",
      "commune": "Colmar",
      "pays": "FR"
    },
    {
      "agg_key": "didenheim|kahlberg diag|noc|noc",
      "match_existing_site_id": null,
      "is_new": true,
      "merge_candidate": false,
      "x_l93": null,
      "y_l93": null,
      "has_coords": false,
      "nom_site": "Didenheim - Kahlberg (diag)",
      "commune": "Didenheim",
      "pays": "FR"
    },
    {
      "agg_key": "gundolsheim|muhlmatt a remplir|noc|noc",
      "match_existing_site_id": null,
      "is_new": true,
      "merge_candidate": false,
      "x_l93": null,
      "y_l93": null,
      "has_coords": false,
      "nom_site": "Gundolsheim - Muhlmatt A REMPLIR",
      "commune": "Gundolsheim",
      "pays": "FR"
    },
    {
      "agg_key": "marckolsheim|schlettstadterfeld|noc|noc",
      "match_existing_site_id": null,
      "is_new": true,
      "merge_candidate": false,
      "x_l93": null,
      "y_l93": null,
      "has_coords": false,
      "nom_site": "Marckolsheim - Schlettstadterfeld",
      "commune": "Marckolsheim",
      "pays": "FR"
    },
    {
      "agg_key": "duntzenheim|lgv inrap|noc|noc",
      "match_existing_site_id": null,
      "is_new": true,
      "merge_candidate": false,
      "x_l93": null,
      "y_l93": null,
      "has_coords": false,
      "nom_site": "Duntzenheim - LGV inrap",
      "commune": "Duntzenheim",
      "pays": "FR"
    },
    {
      "agg_key": "duntzenheim|ebenheit lgv stock nord 2 1|noc|noc",
      "match_existing_site_id": null,
      "is_new": true,
      "merge_candidate": false,
      "x_l93": null,
      "y_l93": null,
      "has_coords": false,
      "nom_site": "Duntzenheim - Ebenheit, LGV stock Nord 2-1",
      "commune": "Duntzenheim",
      "pays": "FR"
    },
    {
      "agg_key": "schnersheim|za behlenheimerweg|noc|noc",
      "match_existing_site_id": null,
      "is_new": true,
      "merge_candidate": false,
      "x_l93": null,
      "y_l93": null,
      "has_coords": false,
      "nom_site": "Schnersheim - ZA Behlenheimerweg",
      "commune": "Schnersheim",
      "pays": "FR"
    }
  ]
}